to_paragraphs/__init__.py
to_paragraphs/to_paragraphs.py
to_paragraphs-0.2.1.dist-info/METADATA
to_paragraphs-0.2.1.dist-info/WHEEL
to_paragraphs-0.2.1.dist-info/RECORD
